stochpy/__init__.py
stochpy/core2/InfixParser.py
stochpy/core2/PyscesCore2.py
stochpy/core2/PyscesCore2Interfaces.py
stochpy/core2/__init__.py
stochpy/core2/lex.py
stochpy/core2/version.py
stochpy/core2/yacc.py
stochpy/implementations/DelayedDirectMethod.py
stochpy/implementations/DelayedNRM.py
stochpy/implementations/DirectMethod.py
stochpy/implementations/FastSingleMoleculeMethod.py
stochpy/implementations/FirstReactionMethod.py
stochpy/implementations/NextReactionMethod.py
stochpy/implementations/SingleMoleculeMethod.py
stochpy/implementations/StochPyTools.py
stochpy/implementations/TauLeaping.py
stochpy/implementations/__init__.py
stochpy/lib/__init__.py
stochpy/lib/lex.py
stochpy/lib/yacc.py
stochpy/modules/Analysis.py
stochpy/modules/PyscesInterfaces.py
stochpy/modules/PyscesMiniModel.py
stochpy/modules/PyscesParse.py
stochpy/modules/SBML2PSC.py
stochpy/modules/SimulatorOutput2StochPy.py
stochpy/modules/StochPyCellDivision.py
stochpy/modules/StochPyCellDivisionPlot.py
stochpy/modules/StochPyDemo.py
stochpy/modules/StochPyPlot.py
stochpy/modules/StochPyPrint.py
stochpy/modules/StochPyUtils.py
stochpy/modules/StochSim.py
stochpy/modules/__init__.py
stochpy/pscmodels/Autoreg.py
stochpy/pscmodels/BirthDeath.py
stochpy/pscmodels/Burstmodel.py
stochpy/pscmodels/CellDivision.py
stochpy/pscmodels/DecayingDimerizing.py
stochpy/pscmodels/GeneDuplication.py
stochpy/pscmodels/ImmigrationDeath.py
stochpy/pscmodels/Isomerization.py
stochpy/pscmodels/Polymerase.py
stochpy/pscmodels/Schlogl.py
stochpy/pscmodels/Signaling3cCD.py
stochpy/pscmodels/SignalingTimeVaryingL.py
stochpy/pscmodels/TranscriptionIntermediate.py
stochpy/pscmodels/__init__.py
stochpy/pscmodels/chain1500.py
stochpy/pscmodels/chain5.py
stochpy/pscmodels/chain50.py
stochpy/pscmodels/chain500.py
stochpy/pscmodels/dsmts_001_01.py
stochpy/pscmodels/dsmts_001_11.py
stochpy/pscmodels/dsmts_001_19.py
stochpy/pscmodels/dsmts_002_10.py
stochpy/pscmodels/dsmts_003_03.py
stochpy/pscmodels/dsmts_003_04.py
stochpy-2.5.dist-info/licenses/LICENSE
stochpy-2.5.dist-info/METADATA
stochpy-2.5.dist-info/WHEEL
stochpy-2.5.dist-info/top_level.txt
stochpy-2.5.dist-info/RECORD
