Metadata-Version: 2.4
Name: StochPy
Version: 2.5
Summary: StochPy (Stochastic modeling in Python) provides several stochastic simulation algorithms to simulate (bio)chemical systems of reactions in a stochastic manner.
Home-page: http://stochpy.sourceforge.net
Download-URL: https://github.com/SystemsBioinformatics/stochpy
Author: T.R. Maarleveld
Author-email: "T.R. Maarleveld" <tmd200@users.sourceforge.net>
Maintainer: Brett Olivier
Maintainer-email: "Brett G. Olivier" <b.g.olivier@vu.nl>
License: BSD License
Project-URL: Homepage, https://github.com/SystemsBioinformatics/stochpy
Project-URL: Download, https://github.com/SystemsBioinformatics/stochpy
Project-URL: Bug Tracker, https://github.com/SystemsBioinformatics/stochpy/issues
Keywords: Bioinformatics,Computational Systems Biology,Modeling,Simulation,Stochastic Simulation Algorithms,Stochastic
Platform: Windows
Platform: Linux
Platform: Mac
Classifier: Development Status :: 5 - Production/Stable
Classifier: Development Status :: 6 - Mature
Classifier: Environment :: Console
Classifier: Intended Audience :: End Users/Desktop
Classifier: Intended Audience :: Science/Research
Classifier: License :: OSI Approved :: BSD License
Classifier: Natural Language :: English
Classifier: Operating System :: OS Independent
Classifier: Programming Language :: Python :: 3.9
Classifier: Programming Language :: Python :: 3.10
Classifier: Programming Language :: Python :: 3.11
Classifier: Programming Language :: Python :: 3.12
Classifier: Topic :: Scientific/Engineering :: Bio-Informatics
Requires-Python: >=3.9
License-File: LICENSE
Requires-Dist: numpy>=1.21.6
Requires-Dist: scipy
Requires-Dist: matplotlib
Dynamic: author
Dynamic: download-url
Dynamic: home-page
Dynamic: license-file
Dynamic: maintainer
Dynamic: platform
Dynamic: requires-python
